nbyt_rss/__init__.py
nbyt_rss/__main__.py
nbyt_rss/exceptions.py
nbyt_rss/getting.py
nbyt_rss/main.py
nbyt_rss-0.5.2.1.dist-info/METADATA
nbyt_rss-0.5.2.1.dist-info/WHEEL
nbyt_rss-0.5.2.1.dist-info/entry_points.txt
nbyt_rss-0.5.2.1.dist-info/RECORD
